napari_assistant_plugin_generator/__init__.py
napari_assistant_plugin_generator/_plugin_generator.py
napari_assistant_plugin_generator-0.1.0.dist-info/LICENSE
napari_assistant_plugin_generator-0.1.0.dist-info/METADATA
napari_assistant_plugin_generator-0.1.0.dist-info/WHEEL
napari_assistant_plugin_generator-0.1.0.dist-info/entry_points.txt
napari_assistant_plugin_generator-0.1.0.dist-info/top_level.txt
napari_assistant_plugin_generator-0.1.0.dist-info/RECORD
