Metadata-Version: 2.1
Name: napari-assistant-plugin-generator
Version: 0.1.0
Summary: Auto-generate python code from within napari to make napari-assistant compatible plugins
Home-page: https://github.com/haesleinhuepf/napari-assistant-plugin-generator/
Author: Robert Haase
Author-email: robert.haase@tu-dresden.de
License: BSD-3-Clause
Project-URL: Bug Tracker, https://github.com/haesleinhuepf/napari-assistant-plugin-generator/issues
Project-URL: Documentation, https://github.com/haesleinhuepf/napari-assistant-plugin-generator/
Project-URL: Source Code, https://github.com/haesleinhuepf/napari-assistant-plugin-generator
Project-URL: User Support, https://forum.image.sc/
Classifier: Framework :: napari
Classifier: License :: OSI Approved :: BSD License
Classifier: Topic :: Scientific/Engineering :: Image Processing
Classifier: Topic :: Scientific/Engineering :: Information Analysis
Classifier: Programming Language :: Python
Classifier: Programming Language :: Python :: 3
Classifier: Programming Language :: Python :: 3.8
Classifier: Programming Language :: Python :: 3.9
Classifier: Operating System :: OS Independent
Requires-Python: >=3.8
License-File: LICENSE
Requires-Dist: napari-plugin-engine (>=0.1.4)
Requires-Dist: magicgui
Requires-Dist: numpy (!=1.19.4)
Requires-Dist: jupytext
Requires-Dist: jupyter
Requires-Dist: dask
Requires-Dist: autopep8
Requires-Dist: cookiecutter
Requires-Dist: napari-tools-menu
Requires-Dist: napari-assistant (>=0.4.1)
